ABOUT.rst
AUTHORS
CHANGELOG
LICENSE
README.md
appveyor.yml
requirements.txt
setup.cfg
setup.py
.idea/encodings.xml
.idea/misc.xml
.idea/modules.xml
.idea/vcs.xml
docs/img/htmlreport.png
docs/img/popup.png
docs/img/qq-international-icon-32.png
docs/img/qqgroup.png
docs/img/settings.png
docs/img/uiautomatorviewer-popup.png
examples/apk_install.py
examples/adbkit-init/README.md
examples/adbkit-init/main.js
examples/adbkit-init/package.json
examples/batteryweb/README.md
examples/batteryweb/main.py
examples/batteryweb/templates/index.html
examples/com.codeskyblue.remotecamera/main_test.py
examples/com.netease.cloudmusic/README.txt
examples/com.netease.cloudmusic/main.py
examples/com.netease.cloudmusic/xpath_test.py
examples/u2iniit-standalone/README.txt
examples/u2iniit-standalone/init-vendor.sh
examples/u2iniit-standalone/main.go
examples/u2iniit-standalone/proxyhttp.go
examples/u2iniit-standalone/uiautomator2-init-standalone.bat
muiautomator/__init__.py
muiautomator/__main__.py
muiautomator/adbutils.py
muiautomator/exceptions.py
muiautomator/messagebox.py
muiautomator/session.py
muiautomator/utils.py
muiautomator/version.py
muiautomator.egg-info/PKG-INFO
muiautomator.egg-info/SOURCES.txt
muiautomator.egg-info/dependency_links.txt
muiautomator.egg-info/entry_points.txt
muiautomator.egg-info/not-zip-safe
muiautomator.egg-info/pbr.json
muiautomator.egg-info/requires.txt
muiautomator.egg-info/top_level.txt
muiautomator/cli/__init__.py
muiautomator/cli/__main__.py
muiautomator/cli/install.py
muiautomator/cli/runyaml.py
muiautomator/ext/__init__.py
muiautomator/ext/aircv/__init__.py
muiautomator/ext/htmlreport/__init__.py
muiautomator/ext/info/__init__.py
muiautomator/ext/info/conf.py
muiautomator/ext/ocr/__init__.py
muiautomator/ext/perf/__init__.py
muiautomator/ext/xpath/__init__.py
tests/test_simple.py