Metadata-Version: 1.1
Name: muiautomator
Version: 0.0.5.dev1
Summary: Python Wrapper for Android UiAutomator2 test tool
Home-page: https://github.com/u1028498345/myuiautomator
Author: liubing
Author-email: 1028498345@qq.com
License: MIT
Platform: UNKNOWN
Classifier: Development Status :: 4 - Beta
Classifier: Environment :: Console
Classifier: Intended Audience :: Developers
Classifier: Operating System :: POSIX
Classifier: Programming Language :: Python :: 2.7
Classifier: Programming Language :: Python :: 3
Classifier: Topic :: Software Development :: Libraries :: Python Modules
Classifier: Topic :: Software Development :: Testing
